tamr_client/__init__.py
tamr_client/_beta.py
tamr_client/_types/__init__.py
tamr_client/_types/attribute.py
tamr_client/_types/auth.py
tamr_client/_types/backup.py
tamr_client/_types/dataset.py
tamr_client/_types/instance.py
tamr_client/_types/json.py
tamr_client/_types/operation.py
tamr_client/_types/project.py
tamr_client/_types/restore.py
tamr_client/_types/session.py
tamr_client/_types/transformations.py
tamr_client/_types/url.py
tamr_client/attribute/__init__.py
tamr_client/attribute/_attribute.py
tamr_client/attribute/sub.py
tamr_client/attribute/type.py
tamr_client/backup.py
tamr_client/categorization/__init__.py
tamr_client/categorization/_categorization.py
tamr_client/categorization/project.py
tamr_client/dataset/__init__.py
tamr_client/dataset/_dataset.py
tamr_client/dataset/dataframe.py
tamr_client/dataset/record.py
tamr_client/dataset/unified.py
tamr_client/exception.py
tamr_client/golden_records/__init__.py
tamr_client/golden_records/_golden_records.py
tamr_client/golden_records/project.py
tamr_client/instance.py
tamr_client/mastering/__init__.py
tamr_client/mastering/_mastering.py
tamr_client/mastering/project.py
tamr_client/operation.py
tamr_client/primary_key.py
tamr_client/project.py
tamr_client/py.typed
tamr_client/response.py
tamr_client/restore.py
tamr_client/schema_mapping/__init__.py
tamr_client/schema_mapping/_schema_mapping.py
tamr_client/schema_mapping/attribute_mapping.py
tamr_client/schema_mapping/project.py
tamr_client/session.py
tamr_client/transformations.py
tamr_unify_client/__init__.py
tamr_unify_client/_ignore_nan_encoder.py
tamr_unify_client/attribute/collection.py
tamr_unify_client/attribute/resource.py
tamr_unify_client/attribute/subattribute.py
tamr_unify_client/attribute/type.py
tamr_unify_client/auth/__init__.py
tamr_unify_client/auth/jwt_token.py
tamr_unify_client/auth/token.py
tamr_unify_client/auth/username_password.py
tamr_unify_client/base_collection.py
tamr_unify_client/base_model.py
tamr_unify_client/base_resource.py
tamr_unify_client-1.7.0.dist-info/LICENSE
tamr_unify_client-1.7.0.dist-info/METADATA
tamr_unify_client-1.7.0.dist-info/WHEEL
tamr_unify_client-1.7.0.dist-info/RECORD
