Metadata-Version: 2.1
Name: tamr-unify-client
Version: 1.7.0
Summary: Python Client for the Tamr API
Home-page: https://tamr-client.readthedocs.io/en/stable/
License: Apache-2.0
Keywords: tamr
Author: Samuel Kalish
Author-email: samuel.kalish@tamr.com
Requires-Python: >=3.7.1,<4.0.0
Classifier: Development Status :: 4 - Beta
Classifier: Intended Audience :: Developers
Classifier: Intended Audience :: Information Technology
Classifier: License :: OSI Approved :: Apache Software License
Classifier: Programming Language :: Python
Classifier: Programming Language :: Python :: 3
Classifier: Programming Language :: Python :: 3.8
Classifier: Programming Language :: Python :: 3.9
Classifier: Programming Language :: Python :: 3.10
Classifier: Programming Language :: Python :: 3.11
Classifier: Programming Language :: Python :: 3
Classifier: Programming Language :: Python :: 3 :: Only
Classifier: Programming Language :: Python :: 3.10
Classifier: Programming Language :: Python :: 3.7
Classifier: Programming Language :: Python :: 3.8
Classifier: Programming Language :: Python :: 3.9
Requires-Dist: requests (>=2.22,<3.0)
Requires-Dist: urllib3 (<2)
Project-URL: Repository, https://github.com/Datatamer/tamr-client
